Metadata-Version: 1.0
Name: multiple-django-popolo-sources
Version: 0.0.2
Summary: Handle django-popolo data from multiple separate sources
Home-page: UNKNOWN
Author: Mark Longair
Author-email: mark@mysociety.org
License: AGPL
Keywords: django popolo civic-tech
Platform: UNKNOWN
